{
  "researchItems": [
    {
      "title": {
        "kor": "OSLabID - OS Lab 멤버용 ID 카드",
        "eng": "OSLabID - ID Card for OS Lab Members"
      },
      "date": "2023-01-01",
      "preview": {
        "kor": "온라인 사이트 및 오프라인에서 연구실 부원의 본인인증을 위해 사용할 수 있는 스마트카드입니다. 기존의 단순 인증 방식에서 벗어나 암호화된 인증 로직을 구현하였습니다.",
        "eng": "A smart card designed for both online and offline authentication of OS Lab members. It improves upon traditional methods by implementing an encrypted authentication logic."
      },
      "img": "/images/Research/sc.jpg",
      "link": {
        "kor": "https://github.com/OS-LAB-DaejinUniv/Smart-Lab/blob/main/smartcard/README.md",
        "eng": "https://github.com/OS-LAB-DaejinUniv/Smart-Lab/blob/main/smartcard/README.md"
      },
      "markdownId": "0"
    },
    {
      "title": {
        "kor": "TinyFS - 로우 풋프린트 파일 시스템",
        "eng": "TinyFS - A Low Footprint Filesystem"
      },
      "date": "2023-02-15",
      "preview": {
        "kor": "임베디드 시스템의 적합성과 리눅스 호환성을 모두 갖춘 파일 시스템입니다. 낮은 메모리 사용량과 데이터 무결성 보장을 특징으로 합니다.",
        "eng": "A file system ensuring compatibility with both embedded systems and Linux. Features include low memory usage and data integrity assurance."
      },
      "img": "/images/Research/fs.png",
      "markdownId": "1"
    },
    {
      "title": {
        "kor": "OSPass - 스마트카드를 통한 안전한 로그인 서비스",
        "eng": "OSPass - Secure Sign-In Service via Smart Card"
      },
      "date": "2023-03-10",
      "preview": {
        "kor": "OAuth 2.0 표준을 준수하는 온라인 부원 인증 서비스로, 기존의 아이디와 비밀번호 없이도 안전하게 로그인이 가능합니다.",
        "eng": "An online authentication service that complies with OAuth 2.0 standards, allowing secure login without traditional username and password credentials."
      },
      "img": "/images/Research/ospass.png",
      "link": {
        "kor": "https://github.com/OS-LAB-DaejinUniv/OSPass",
        "eng": "https://github.com/OS-LAB-DaejinUniv/OSPass"
      },
      "markdownId": "2"
    },
    {
      "title": {
        "kor": "SmartLab API - 실내 자동화 API",
        "eng": "SmartLab API - Indoor Automation API"
      },
      "date": "2023-04-05",
      "preview": {
        "kor": "스마트홈과 유사한 IoT 서비스를 연구실 내에서 구현하기 위한 프로젝트입니다. 실내 가전의 상태 모니터링과 제어 기능을 제공합니다.",
        "eng": "A project aimed at implementing IoT services similar to smart homes within the lab. Provides monitoring of appliance statuses and remote control capabilities."
      },
      "img": "/images/Research/sl.png",
      "link": {
        "kor": "http://jay.oslab/smartlab",
        "eng": "http://jay.oslab/smartlab"
      },
      "markdownId": "3"
    }
  ]
}
